json_diff.py
json_diff-1.4.1.dist-info/top_level.txt
json_diff-1.4.1.dist-info/entry_points.txt
json_diff-1.4.1.dist-info/METADATA
json_diff-1.4.1.dist-info/DESCRIPTION.rst
json_diff-1.4.1.dist-info/metadata.json
json_diff-1.4.1.dist-info/WHEEL
json_diff-1.4.1.dist-info/RECORD
