Metadata-Version: 2.0
Name: json-diff
Version: 1.4.1
Summary: Generates diff between two JSON files
Home-page: https://gitlab.com/mcepl/json_diff
Author: Matěj Cepl
Author-email: mcepl@cepl.eu
License: UNKNOWN
Keywords: json,diff
Platform: UNKNOWN
Classifier: Programming Language :: Python
Classifier: Development Status :: 4 - Beta
Classifier: Environment :: Console
Classifier: Intended Audience :: Information Technology
Classifier: License :: OSI Approved :: MIT License
Classifier: Operating System :: OS Independent
Classifier: Topic :: Software Development :: Libraries :: Python Modules
Classifier: Topic :: Text Processing :: General
